ravendb_embedded/__init__.py
ravendb_embedded/embedded_server.py
ravendb_embedded/options.py
ravendb_embedded/provide.py
ravendb_embedded/raven_server_runner.py
ravendb_embedded/runtime_framework_version_matcher.py
ravendb_embedded/target/nuget/.signature.p7s
ravendb_embedded/target/nuget/LICENSE.txt
ravendb_embedded/target/nuget/README.md
ravendb_embedded/target/nuget/RavenDB.Embedded.nuspec
ravendb_embedded/target/nuget/[Content_Types].xml
ravendb_embedded/target/nuget/icon.png
ravendb_embedded/target/nuget/_rels/.rels
ravendb_embedded/target/nuget/build/RavenDB.Embedded.targets
ravendb_embedded/target/nuget/contentFiles/any/any/RavenDBServer/AWSSDK.Core.dll
ravendb_embedded/target/nuget/contentFiles/any/any/RavenDBServer/AWSSDK.Glacier.dll
ravendb_embedded/target/nuget/contentFiles/any/any/RavenDBServer/AWSSDK.S3.dll
ravendb_embedded/target/nuget/contentFiles/any/any/RavenDBServer/AWSSDK.SQS.dll
ravendb_embedded/target/nuget/contentFiles/any/any/RavenDBServer/AWSSDK.SimpleNotificationService.dll
ravendb_embedded/target/nuget/contentFiles/any/any/RavenDBServer/Acornima.dll
ravendb_embedded/target/nuget/contentFiles/any/any/RavenDBServer/Amqp.Net.dll
ravendb_embedded/target/nuget/contentFiles/any/any/RavenDBServer/Amqp.Serialization.dll
ravendb_embedded/target/nuget/contentFiles/any/any/RavenDBServer/Apache.Arrow.dll
ravendb_embedded/target/nuget/contentFiles/any/any/RavenDBServer/Azure.AI.OpenAI.dll
ravendb_embedded/target/nuget/contentFiles/any/any/RavenDBServer/Azure.Core.dll
ravendb_embedded/target/nuget/contentFiles/any/any/RavenDBServer/Azure.Identity.dll
ravendb_embedded/target/nuget/contentFiles/any/any/RavenDBServer/Azure.Storage.Blobs.dll
ravendb_embedded/target/nuget/contentFiles/any/any/RavenDBServer/Azure.Storage.Common.dll
ravendb_embedded/target/nuget/contentFiles/any/any/RavenDBServer/Azure.Storage.Queues.dll
ravendb_embedded/target/nuget/contentFiles/any/any/RavenDBServer/BouncyCastle.Cryptography.dll
ravendb_embedded-7.1.2.post1.dist-info/METADATA
ravendb_embedded-7.1.2.post1.dist-info/WHEEL
ravendb_embedded-7.1.2.post1.dist-info/top_level.txt
ravendb_embedded-7.1.2.post1.dist-info/RECORD
