Metadata-Version: 2.4
Name: ravendb-embedded
Version: 7.1.2.post1
Summary: RavenDB Embedded library to run RavenDB in an embedded way
Home-page: https://github.com/ravendb/ravendb-python-embedded
Author: RavenDB
Author-email: support@ravendb.net
License: Custom EULA
Keywords: ravendb embedded database nosql doc db
Requires-Python: >=3.9
Requires-Dist: ravendb~=7.1.2
Requires-Dist: cryptography~=42.0.0
Dynamic: author
Dynamic: author-email
Dynamic: description
Dynamic: home-page
Dynamic: keywords
Dynamic: license
Dynamic: requires-dist
Dynamic: requires-python
Dynamic: summary
